depinj/__init__.py
depinj/depinj.py
depinj-0.1.1.dist-info/LICENSE
depinj-0.1.1.dist-info/METADATA
depinj-0.1.1.dist-info/WHEEL
depinj-0.1.1.dist-info/top_level.txt
depinj-0.1.1.dist-info/RECORD
