Metadata-Version: 2.1
Name: depinj
Version: 0.1.1
Summary: A friendly dependency injection package
Home-page: https://github.com/rcmarc/depinj
Author: Marcos Carrera
Author-email: ramoscarrer@gmail.com
License: UNKNOWN
Project-URL: Bug Tracker, https://github.com/rcmarc/depinj/issues
Platform: UNKNOWN
Classifier: Programming Language :: Python :: 3
Classifier: License :: OSI Approved :: MIT License
Classifier: Operating System :: OS Independent
Requires-Python: >=3.6
License-File: LICENSE
